potentiostat_data_parser/__init__.py
potentiostat_data_parser/_modidx.py
potentiostat_data_parser/chi.py
potentiostat_data_parser/palmsens.py
potentiostat_data_parser-0.0.5.dist-info/licenses/LICENSE
potentiostat_data_parser-0.0.5.dist-info/METADATA
potentiostat_data_parser-0.0.5.dist-info/WHEEL
potentiostat_data_parser-0.0.5.dist-info/entry_points.txt
potentiostat_data_parser-0.0.5.dist-info/top_level.txt
potentiostat_data_parser-0.0.5.dist-info/RECORD
